{
    "features": [
      {
        "type": "Feature",
        "properties": {
          "COUNTRY": "France",
          "Region": "Normandie",
          "Departement": "Manche",
          "Nom": "Barfleur",
          "Code": "50760"
        },
        "geometry": {
          "type": "Point",
          "coordinates": [49.67061, -1.26376]
        }
      },
      {
        "type": "Feature",
        "properties": {
          "COUNTRY": "France",
          "Region": "Normandie",
          "Departement": "Manche",
          "Nom": "Fermanville",
          "Code": "50840"
        },
        "geometry": {
          "type": "Point",
          "coordinates": [49.67675, -1.46816]
        }
      }
    ]
}